<?xml version = '1.0' encoding = 'UTF-8'?>
<DomainFile class="oracle.dbtools.crest.model.design.DomainFileWrapper" fileName="ddlProjekt_Domains">
<domains>
<Domain class="oracle.dbtools.crest.model.design.Domain" name="VARCHAR_0_0_0" id="506FCE27-D552-2667-283E-E0F91B5F02AC">
<createdBy>ficek</createdBy>
<createdTime>2025-03-31 14:34:35 UTC</createdTime>
<ownerDesignName>projektModeler</ownerDesignName>
<avTSortOrder>0</avTSortOrder>
<fileName>ddlProjekt_Domains</fileName>
<logicalDatatype>LOGDT024</logicalDatatype>
</Domain>
<Domain class="oracle.dbtools.crest.model.design.Domain" name="Integer_0_0_0" id="96190E8F-882F-2CEA-4DB3-B3BBFD29E766">
<createdBy>ficek</createdBy>
<createdTime>2025-03-31 14:34:35 UTC</createdTime>
<ownerDesignName>projektModeler</ownerDesignName>
<avTSortOrder>0</avTSortOrder>
<fileName>ddlProjekt_Domains</fileName>
<logicalDatatype>LOGDT011</logicalDatatype>
</Domain>
</domains>
</DomainFile>
